LICENSE
MANIFEST.in
README.rst
setup.py
sentry_uploads/__init__.py
sentry_uploads/interfaces.py
sentry_uploads/models.py
sentry_uploads/plugin.py
sentry_uploads.egg-info/PKG-INFO
sentry_uploads.egg-info/SOURCES.txt
sentry_uploads.egg-info/dependency_links.txt
sentry_uploads.egg-info/entry_points.txt
sentry_uploads.egg-info/not-zip-safe
sentry_uploads.egg-info/requires.txt
sentry_uploads.egg-info/top_level.txt
sentry_uploads/scripts/__init__.py
sentry_uploads/scripts/runner.py
sentry_uploads/templates/sentry_uploads/test.html
sentry_uploads/templates/sentry_uploads/uploads.html
sentry_uploads/templates/sentry_uploads/uploads.txt