Metadata-Version: 1.1
Name: sentry-uploads
Version: 0.1.0
Summary: A Sentry extension which allows file uploads.
Home-page: http://github.com/duaneg/sentry-uploads
Author: Duane Griffin
Author-email: duaneg@dghda.com
License: BSD
Platform: UNKNOWN
Classifier: Framework :: Django
Classifier: Intended Audience :: Developers
Classifier: Intended Audience :: System Administrators
Classifier: Operating System :: OS Independent
Classifier: Topic :: Software Development
